node.py
p2p_messenger_app-1.0.39.dist-info/METADATA
p2p_messenger_app-1.0.39.dist-info/WHEEL
p2p_messenger_app-1.0.39.dist-info/entry_points.txt
p2p_messenger_app-1.0.39.dist-info/top_level.txt
p2p_messenger_app-1.0.39.dist-info/RECORD
