Metadata-Version: 2.4
Name: p2p_messenger_app
Version: 1.0.39
Summary: Aplicación de chat P2P con salas de chat
Home-page: https://github.com/alfonsohernandezgonzalez/p2p_messenger
Author: Alfonso Hernández González
Author-email: alfonsohernandezgonzalez@gmail.com
Classifier: Programming Language :: Python :: 3
Classifier: License :: OSI Approved :: MIT License
Classifier: Operating System :: OS Independent
Requires-Python: >=3.6
Requires-Dist: cryptography==42.0.2
Requires-Dist: pycryptodome==3.20.0
Requires-Dist: psutil
Requires-Dist: requests
Dynamic: author
Dynamic: author-email
Dynamic: classifier
Dynamic: description
Dynamic: description-content-type
Dynamic: home-page
Dynamic: requires-dist
Dynamic: requires-python
Dynamic: summary
